setup.py
btable/__init__.py
btable/data/table.btable
btable/data/unicode.btable
btable_py.egg-info/PKG-INFO
btable_py.egg-info/SOURCES.txt
btable_py.egg-info/dependency_links.txt
btable_py.egg-info/top_level.txt