Metadata-Version: 1.0
Name: btable-py
Version: 0.1.0
Summary: A binary serialization format for sparse, labeled 2D numeric datasets
Home-page: https://github.com/framed-data/btable-py
Author: Andrew Berls
Author-email: andrew@framed.io
License: UNKNOWN
Platform: UNKNOWN
